qwery/__init__.py
qwery/test_qwery.py
qwery-0.0.1.dist-info/METADATA
qwery-0.0.1.dist-info/WHEEL
qwery-0.0.1.dist-info/top_level.txt
qwery-0.0.1.dist-info/RECORD
