Metadata-Version: 2.1
Name: qwery
Version: 0.0.1
Summary: small and lightweight query builder and data layer based on Pydantic and asyncpg
Home-page: UNKNOWN
License: UNKNOWN
Platform: UNKNOWN
Classifier: Programming Language :: Python :: 3
Classifier: License :: OSI Approved :: MIT License
Classifier: Operating System :: OS Independent
Requires-Python: >=3.8
Requires-Dist: asyncpg (==0.20.1)
Requires-Dist: pydantic (==1.5.1)
